fsleyes_plugin_mrs/__init__.py
fsleyes_plugin_mrs/constants.py
fsleyes_plugin_mrs/controls.py
fsleyes_plugin_mrs/default_colourscheme.json
fsleyes_plugin_mrs/default_mrsi.tree
fsleyes_plugin_mrs/layouts.py
fsleyes_plugin_mrs/overlaylistpanel.py
fsleyes_plugin_mrs/profiles.py
fsleyes_plugin_mrs/series.py
fsleyes_plugin_mrs/tools.py
fsleyes_plugin_mrs/views.py
fsleyes_plugin_mrs/icons/nifti_mrs_icon-mrs_icon.png
fsleyes_plugin_mrs/icons/nifti_mrs_icon-mrs_icon_highlight.png
fsleyes_plugin_mrs/icons/nifti_mrs_icon-mrs_icon_highlight_thumb24.png
fsleyes_plugin_mrs/icons/nifti_mrs_icon-mrs_icon_highlight_thumb24@2x.png
fsleyes_plugin_mrs/icons/nifti_mrs_icon-mrs_icon_thumb24.png
fsleyes_plugin_mrs/icons/nifti_mrs_icon-mrs_icon_thumb24@2x.png
fsleyes_plugin_mrs-0.1.5.post1.dist-info/licenses/LICENSE
fsleyes_plugin_mrs-0.1.5.post1.dist-info/METADATA
fsleyes_plugin_mrs-0.1.5.post1.dist-info/WHEEL
fsleyes_plugin_mrs-0.1.5.post1.dist-info/entry_points.txt
fsleyes_plugin_mrs-0.1.5.post1.dist-info/top_level.txt
fsleyes_plugin_mrs-0.1.5.post1.dist-info/RECORD
