Metadata-Version: 2.4
Name: fsleyes-plugin-mrs
Version: 0.1.5.post1
Summary: FSLeyes extension for viewing MRS(I) data formatted as NIfTI-MRS.
Home-page: https://git.fmrib.ox.ac.uk/wclarke/fsleyes-plugin-mrs
Author: William Clarke, University of Oxford
Author-email: william.clarke@ndcn.ox.ac.uk
Classifier: Programming Language :: Python :: 3
Classifier: Programming Language :: Python :: 3.11
Classifier: Programming Language :: Python :: 3.12
Classifier: Programming Language :: Python :: 3.13
Classifier: Programming Language :: Python :: 3.14
Classifier: License :: OSI Approved :: BSD License
Classifier: Operating System :: OS Independent
Requires-Python: >=3.11
License-File: LICENSE
Requires-Dist: fsleyes<2.0,>=1.0.10
Requires-Dist: fsleyes-widgets<1.0,>=0.16.0
Requires-Dist: file-tree<2.0,>=1.6.1
Requires-Dist: seaborn<1.0,>=0.12.0
Dynamic: author
Dynamic: author-email
Dynamic: classifier
Dynamic: description
Dynamic: description-content-type
Dynamic: home-page
Dynamic: license-file
Dynamic: requires-dist
Dynamic: requires-python
Dynamic: summary
